{"startnode":"23b4364d-057a-4eb8-847b-4ef52a7f0bd7","nodemodels":[{"classname":"QuadNode","guid":"1649b756-3c8c-44ae-a63d-52621afaaf1d","params":[],"values":[{"name":"x","value":238},{"name":"y","value":156},{"name":"w","value":500},{"name":"h","value":680}],"childNodes":["9e3ab11d-7b03-4324-9bfe-ab5fcd2365f5","6263c50a-1b6d-4991-9e7d-968a278a754b"]},{"classname":"FillNode","guid":"9e3ab11d-7b03-4324-9bfe-ab5fcd2365f5","params":[],"values":[{"name":"opacity","value":1},{"name":"clipMask","value":false},{"name":"blendMode","value":"normal"}],"childNodes":[]},{"classname":"QuadSubdivisionNode","guid":"6263c50a-1b6d-4991-9e7d-968a278a754b","params":[],"values":[{"name":"nRows","value":5},{"name":"nCols","value":5}],"childNodes":["f3958fd9-b3e9-4e69-9be6-308ef710e351"]},{"classname":"FloatParam","guid":"bb64e3a9-1651-4c46-806b-f446a53d23f5","params":[],"values":[{"name":"value","value":12}]},{"classname":"RotatePathIndexNode","guid":"e09867e9-f21e-4319-892a-7858d61c9c6a","params":[{"key":"shift","object":"063f4f05-1f03-43b6-a2ec-4c799d0f50ec","outputName":""}],"values":[{"name":"shift","value":2}],"childNodes":["80403072-6d91-41fa-a229-cc64d1aec5b5"]},{"classname":"RandomIntInRangeParam","guid":"063f4f05-1f03-43b6-a2ec-4c799d0f50ec","params":[],"values":[{"name":"value","value":0},{"name":"startIndex","value":0},{"name":"endIndex","value":3}]},{"classname":"QuadToTriNode","guid":"80403072-6d91-41fa-a229-cc64d1aec5b5","params":[],"values":[{"name":"p0","value":{"classname":"Point","x":0,"y":0}},{"name":"p1","value":{"classname":"Point","x":1,"y":0}},{"name":"p2","value":{"classname":"Point","x":0,"y":1}}],"childNodes":["9e3ab11d-7b03-4324-9bfe-ab5fcd2365f5"]},{"classname":"RandomColourFromSetNode","guid":"f3958fd9-b3e9-4e69-9be6-308ef710e351","params":[],"values":[{"name":"colourset","value":[{"classname":"Color","r":0.7294117647058823,"g":0.1843137254901961,"b":0.11372549019607843},{"classname":"Color","r":1,"g":0.9725490196078431,"b":0.6431372549019608},{"classname":"Color","r":0.9607843137254902,"g":0.9019607843137255,"b":0.4980392156862745},{"classname":"Color","r":0.14901960784313725,"g":0.2901960784313726,"b":0.34901960784313724},{"classname":"Color","r":0.11764705882352941,"g":0.17254901960784313,"b":0.18823529411764706}]}],"childNodes":["e09867e9-f21e-4319-892a-7858d61c9c6a"]}],"nodeviews":[{"guid":"23b4364d-057a-4eb8-847b-4ef52a7f0bd7","deletable":false,"position":{"x":339,"y":100},"classname":"PatternNodeView","nodemodel":"1649b756-3c8c-44ae-a63d-52621afaaf1d"},{"guid":"7555c6dc-7069-4de7-a079-de0705b22c7c","deletable":true,"position":{"x":390,"y":853},"classname":"PatternNodeView","nodemodel":"9e3ab11d-7b03-4324-9bfe-ab5fcd2365f5"},{"guid":"e6b374e9-5d80-48b9-93e1-e922ee23c667","deletable":true,"position":{"x":594.2182723924677,"y":271.55862010943105},"classname":"PatternNodeView","nodemodel":"6263c50a-1b6d-4991-9e7d-968a278a754b"},{"guid":"7188dd42-f1ba-4c88-95ed-4dcecfa05ae1","deletable":true,"position":{"x":678.7981808565462,"y":82.83134528652448},"classname":"ParamNodeView","nodemodel":"bb64e3a9-1651-4c46-806b-f446a53d23f5"},{"guid":"1b9d6e6d-ce86-42b8-8493-59cde575c71c","deletable":true,"position":{"x":559.1795009420209,"y":560.1940936406543},"classname":"PatternNodeView","nodemodel":"e09867e9-f21e-4319-892a-7858d61c9c6a"},{"guid":"a9ea0d26-45b9-4246-b131-a9e6644dcbde","deletable":true,"position":{"x":810.1604754813359,"y":434.78440885453415},"classname":"ParamNodeView","nodemodel":"063f4f05-1f03-43b6-a2ec-4c799d0f50ec"},{"guid":"76fd67c7-025b-47d1-9e02-4ae740ab58f9","deletable":true,"position":{"x":526.4720656809079,"y":686.8563721977303},"classname":"PatternNodeView","nodemodel":"80403072-6d91-41fa-a229-cc64d1aec5b5"},{"guid":"79b16820-a341-49b2-aa3f-59c857a1beca","deletable":true,"position":{"x":594.9652948032104,"y":393.51508788643514},"classname":"PatternNodeView","nodemodel":"f3958fd9-b3e9-4e69-9be6-308ef710e351"}]}